{"primaryContentSections":[{"kind":"declarations","declarations":[{"tokens":[{"kind":"keyword","text":"init"},{"kind":"text","text":"("},{"kind":"externalParam","text":"rp"},{"kind":"text","text":": "},{"kind":"typeIdentifier","identifier":"doc:\/\/com.ibm.iOS-SDK\/documentation\/FIDO2\/PublicKeyCredentialRpEntity","preciseIdentifier":"s:5FIDO227PublicKeyCredentialRpEntityV","text":"PublicKeyCredentialRpEntity"},{"kind":"text","text":", "},{"kind":"externalParam","text":"user"},{"kind":"text","text":": "},{"kind":"typeIdentifier","identifier":"doc:\/\/com.ibm.iOS-SDK\/documentation\/FIDO2\/PublicKeyCredentialUserEntity","preciseIdentifier":"s:5FIDO229PublicKeyCredentialUserEntityV","text":"PublicKeyCredentialUserEntity"},{"kind":"text","text":", "},{"kind":"externalParam","text":"challenge"},{"kind":"text","text":": "},{"kind":"typeIdentifier","text":"String","preciseIdentifier":"s:SS"},{"kind":"text","text":", "},{"kind":"externalParam","text":"timeout"},{"kind":"text","text":": "},{"kind":"typeIdentifier","text":"Int","preciseIdentifier":"s:Si"},{"kind":"text","text":" = 30000, "},{"kind":"externalParam","text":"excludeCredentials"},{"kind":"text","text":": ["},{"kind":"typeIdentifier","identifier":"doc:\/\/com.ibm.iOS-SDK\/documentation\/FIDO2\/PublicKeyCredentialDescriptor","preciseIdentifier":"s:5FIDO229PublicKeyCredentialDescriptorV","text":"PublicKeyCredentialDescriptor"},{"kind":"text","text":"] = [PublicKeyCredentialDescriptor](), "},{"kind":"externalParam","text":"authenticatorSelection"},{"kind":"text","text":": "},{"kind":"typeIdentifier","identifier":"doc:\/\/com.ibm.iOS-SDK\/documentation\/FIDO2\/AuthenticatorSelectionCriteria","preciseIdentifier":"s:5FIDO230AuthenticatorSelectionCriteriaV","text":"AuthenticatorSelectionCriteria"},{"kind":"text","text":", "},{"kind":"externalParam","text":"attestation"},{"kind":"text","text":": "},{"kind":"typeIdentifier","identifier":"doc:\/\/com.ibm.iOS-SDK\/documentation\/FIDO2\/AttestationConveyancePreference","preciseIdentifier":"s:5FIDO231AttestationConveyancePreferenceO","text":"AttestationConveyancePreference"},{"kind":"text","text":" = .none, "},{"kind":"externalParam","text":"pubKeyCredParams"},{"kind":"text","text":": ["},{"kind":"typeIdentifier","identifier":"doc:\/\/com.ibm.iOS-SDK\/documentation\/FIDO2\/PublicKeyCredentialParameters","preciseIdentifier":"s:5FIDO229PublicKeyCredentialParametersV","text":"PublicKeyCredentialParameters"},{"kind":"text","text":"] = [PublicKeyCredentialParameters(alg: .es256)])"}],"languages":["swift"],"platforms":["iOS"]}]},{"kind":"parameters","parameters":[{"name":"rp","content":[{"type":"paragraph","inlineContent":[{"type":"text","text":"Represents relying party attributes provided when a credential is created."}]}]},{"name":"user","content":[{"type":"paragraph","inlineContent":[{"type":"text","text":"Represents user account information provided when a credential is created."}]}]},{"name":"challenge","content":[{"type":"paragraph","inlineContent":[{"type":"text","text":"The challenge to be used for generating the newly created credential’s attestation object."}]}]},{"name":"pubKeyCredParams","content":[{"type":"paragraph","inlineContent":[{"type":"text","text":"Represents additional options provided when a credential is created."}]}]},{"name":"timeout","content":[{"type":"paragraph","inlineContent":[{"type":"text","text":"The time in milliseconds, that the caller is willing to wait for the call to complete.  Default is 30000 milliseconds."}]}]},{"name":"excludeCredentials","content":[{"type":"paragraph","inlineContent":[{"type":"text","text":"Represents credential parameters to be used for FIDO2 registration or authentication."}]}]},{"name":"authenticatorSelection","content":[{"type":"paragraph","inlineContent":[{"type":"text","text":"Represents configuration items related to the authenticator, which are specified by the WebAuthn relying party."}]}]},{"name":"attestation","content":[{"type":"paragraph","inlineContent":[{"type":"text","text":"Represents credential passing preferences, which are used by the WebAuthn relying party when the credential is created."}]}]}]}],"schemaVersion":{"major":0,"minor":3,"patch":0},"sections":[],"variants":[{"paths":["\/documentation\/fido2\/publickeycredentialcreationoptions\/init(rp:user:challenge:timeout:excludecredentials:authenticatorselection:attestation:pubkeycredparams:)"],"traits":[{"interfaceLanguage":"swift"}]}],"identifier":{"url":"doc:\/\/com.ibm.iOS-SDK\/documentation\/FIDO2\/PublicKeyCredentialCreationOptions\/init(rp:user:challenge:timeout:excludeCredentials:authenticatorSelection:attestation:pubKeyCredParams:)","interfaceLanguage":"swift"},"abstract":[{"type":"text","text":"Creates a new "},{"type":"codeVoice","code":"PublicKeyCredentialCreationOptions"},{"type":"text","text":" instance."}],"kind":"symbol","metadata":{"fragments":[{"kind":"identifier","text":"init"},{"kind":"text","text":"("},{"kind":"externalParam","text":"rp"},{"kind":"text","text":": "},{"kind":"typeIdentifier","text":"PublicKeyCredentialRpEntity","preciseIdentifier":"s:5FIDO227PublicKeyCredentialRpEntityV"},{"kind":"text","text":", "},{"kind":"externalParam","text":"user"},{"kind":"text","text":": "},{"kind":"typeIdentifier","text":"PublicKeyCredentialUserEntity","preciseIdentifier":"s:5FIDO229PublicKeyCredentialUserEntityV"},{"kind":"text","text":", "},{"kind":"externalParam","text":"challenge"},{"kind":"text","text":": "},{"kind":"typeIdentifier","text":"String","preciseIdentifier":"s:SS"},{"kind":"text","text":", "},{"kind":"externalParam","text":"timeout"},{"kind":"text","text":": "},{"kind":"typeIdentifier","text":"Int","preciseIdentifier":"s:Si"},{"kind":"text","text":", "},{"kind":"externalParam","text":"excludeCredentials"},{"kind":"text","text":": ["},{"kind":"typeIdentifier","text":"PublicKeyCredentialDescriptor","preciseIdentifier":"s:5FIDO229PublicKeyCredentialDescriptorV"},{"kind":"text","text":"], "},{"kind":"externalParam","text":"authenticatorSelection"},{"kind":"text","text":": "},{"kind":"typeIdentifier","text":"AuthenticatorSelectionCriteria","preciseIdentifier":"s:5FIDO230AuthenticatorSelectionCriteriaV"},{"kind":"text","text":", "},{"kind":"externalParam","text":"attestation"},{"kind":"text","text":": "},{"kind":"typeIdentifier","text":"AttestationConveyancePreference","preciseIdentifier":"s:5FIDO231AttestationConveyancePreferenceO"},{"kind":"text","text":", "},{"kind":"externalParam","text":"pubKeyCredParams"},{"kind":"text","text":": ["},{"kind":"typeIdentifier","text":"PublicKeyCredentialParameters","preciseIdentifier":"s:5FIDO229PublicKeyCredentialParametersV"},{"kind":"text","text":"])"}],"title":"init(rp:user:challenge:timeout:excludeCredentials:authenticatorSelection:attestation:pubKeyCredParams:)","roleHeading":"Initializer","role":"symbol","symbolKind":"init","externalID":"s:5FIDO234PublicKeyCredentialCreationOptionsV2rp4user9challenge7timeout18excludeCredentials22authenticatorSelection11attestation03pubC10CredParamsAcA0bcD8RpEntityV_AA0bcd4UserT0VSSSiSayAA0bcD10DescriptorVGAA013AuthenticatorN8CriteriaVAA31AttestationConveyancePreferenceOSayAA0bcD10ParametersVGtcfc","modules":[{"name":"FIDO2"}]},"hierarchy":{"paths":[["doc:\/\/com.ibm.iOS-SDK\/documentation\/FIDO2","doc:\/\/com.ibm.iOS-SDK\/documentation\/FIDO2\/PublicKeyCredentialCreationOptions"]]},"references":{"doc://com.ibm.iOS-SDK/documentation/FIDO2/PublicKeyCredentialDescriptor":{"role":"symbol","title":"PublicKeyCredentialDescriptor","fragments":[{"kind":"keyword","text":"struct"},{"kind":"text","text":" "},{"kind":"identifier","text":"PublicKeyCredentialDescriptor"}],"abstract":[{"type":"text","text":"Represents credential parameters to be used for FIDO2 registration or authentication."}],"identifier":"doc:\/\/com.ibm.iOS-SDK\/documentation\/FIDO2\/PublicKeyCredentialDescriptor","kind":"symbol","type":"topic","navigatorTitle":[{"kind":"identifier","text":"PublicKeyCredentialDescriptor"}],"url":"\/documentation\/fido2\/publickeycredentialdescriptor"},"doc://com.ibm.iOS-SDK/documentation/FIDO2/PublicKeyCredentialCreationOptions":{"role":"symbol","title":"PublicKeyCredentialCreationOptions","fragments":[{"kind":"keyword","text":"struct"},{"kind":"text","text":" "},{"kind":"identifier","text":"PublicKeyCredentialCreationOptions"}],"abstract":[{"type":"text","text":"Represents options provided when an authentication credential is created."}],"identifier":"doc:\/\/com.ibm.iOS-SDK\/documentation\/FIDO2\/PublicKeyCredentialCreationOptions","kind":"symbol","type":"topic","navigatorTitle":[{"kind":"identifier","text":"PublicKeyCredentialCreationOptions"}],"url":"\/documentation\/fido2\/publickeycredentialcreationoptions"},"doc://com.ibm.iOS-SDK/documentation/FIDO2/AttestationConveyancePreference":{"role":"symbol","title":"AttestationConveyancePreference","fragments":[{"kind":"keyword","text":"enum"},{"kind":"text","text":" "},{"kind":"identifier","text":"AttestationConveyancePreference"}],"abstract":[{"type":"text","text":"An enumeraton for defining credential passing preferences, which are used by the WebAuthn relying party when the credential is created."}],"identifier":"doc:\/\/com.ibm.iOS-SDK\/documentation\/FIDO2\/AttestationConveyancePreference","kind":"symbol","type":"topic","navigatorTitle":[{"kind":"identifier","text":"AttestationConveyancePreference"}],"url":"\/documentation\/fido2\/attestationconveyancepreference"},"doc://com.ibm.iOS-SDK/documentation/FIDO2/PublicKeyCredentialCreationOptions/init(rp:user:challenge:timeout:excludeCredentials:authenticatorSelection:attestation:pubKeyCredParams:)":{"role":"symbol","title":"init(rp:user:challenge:timeout:excludeCredentials:authenticatorSelection:attestation:pubKeyCredParams:)","fragments":[{"kind":"identifier","text":"init"},{"kind":"text","text":"("},{"kind":"externalParam","text":"rp"},{"kind":"text","text":": "},{"kind":"typeIdentifier","text":"PublicKeyCredentialRpEntity","preciseIdentifier":"s:5FIDO227PublicKeyCredentialRpEntityV"},{"kind":"text","text":", "},{"kind":"externalParam","text":"user"},{"kind":"text","text":": "},{"kind":"typeIdentifier","text":"PublicKeyCredentialUserEntity","preciseIdentifier":"s:5FIDO229PublicKeyCredentialUserEntityV"},{"kind":"text","text":", "},{"kind":"externalParam","text":"challenge"},{"kind":"text","text":": "},{"kind":"typeIdentifier","text":"String","preciseIdentifier":"s:SS"},{"kind":"text","text":", "},{"kind":"externalParam","text":"timeout"},{"kind":"text","text":": "},{"kind":"typeIdentifier","text":"Int","preciseIdentifier":"s:Si"},{"kind":"text","text":", "},{"kind":"externalParam","text":"excludeCredentials"},{"kind":"text","text":": ["},{"kind":"typeIdentifier","text":"PublicKeyCredentialDescriptor","preciseIdentifier":"s:5FIDO229PublicKeyCredentialDescriptorV"},{"kind":"text","text":"], "},{"kind":"externalParam","text":"authenticatorSelection"},{"kind":"text","text":": "},{"kind":"typeIdentifier","text":"AuthenticatorSelectionCriteria","preciseIdentifier":"s:5FIDO230AuthenticatorSelectionCriteriaV"},{"kind":"text","text":", "},{"kind":"externalParam","text":"attestation"},{"kind":"text","text":": "},{"kind":"typeIdentifier","text":"AttestationConveyancePreference","preciseIdentifier":"s:5FIDO231AttestationConveyancePreferenceO"},{"kind":"text","text":", "},{"kind":"externalParam","text":"pubKeyCredParams"},{"kind":"text","text":": ["},{"kind":"typeIdentifier","text":"PublicKeyCredentialParameters","preciseIdentifier":"s:5FIDO229PublicKeyCredentialParametersV"},{"kind":"text","text":"])"}],"abstract":[{"type":"text","text":"Creates a new "},{"type":"codeVoice","code":"PublicKeyCredentialCreationOptions"},{"type":"text","text":" instance."}],"identifier":"doc:\/\/com.ibm.iOS-SDK\/documentation\/FIDO2\/PublicKeyCredentialCreationOptions\/init(rp:user:challenge:timeout:excludeCredentials:authenticatorSelection:attestation:pubKeyCredParams:)","kind":"symbol","type":"topic","url":"\/documentation\/fido2\/publickeycredentialcreationoptions\/init(rp:user:challenge:timeout:excludecredentials:authenticatorselection:attestation:pubkeycredparams:)"},"doc://com.ibm.iOS-SDK/documentation/FIDO2/PublicKeyCredentialRpEntity":{"role":"symbol","title":"PublicKeyCredentialRpEntity","fragments":[{"kind":"keyword","text":"struct"},{"kind":"text","text":" "},{"kind":"identifier","text":"PublicKeyCredentialRpEntity"}],"abstract":[{"type":"text","text":"Represents relying party attributes provided when a credential is created."}],"identifier":"doc:\/\/com.ibm.iOS-SDK\/documentation\/FIDO2\/PublicKeyCredentialRpEntity","kind":"symbol","type":"topic","navigatorTitle":[{"kind":"identifier","text":"PublicKeyCredentialRpEntity"}],"url":"\/documentation\/fido2\/publickeycredentialrpentity"},"doc://com.ibm.iOS-SDK/documentation/FIDO2/PublicKeyCredentialParameters":{"role":"symbol","title":"PublicKeyCredentialParameters","fragments":[{"kind":"keyword","text":"struct"},{"kind":"text","text":" "},{"kind":"identifier","text":"PublicKeyCredentialParameters"}],"abstract":[{"type":"text","text":"Represents additional parameters when creating a new credential."}],"identifier":"doc:\/\/com.ibm.iOS-SDK\/documentation\/FIDO2\/PublicKeyCredentialParameters","kind":"symbol","type":"topic","navigatorTitle":[{"kind":"identifier","text":"PublicKeyCredentialParameters"}],"url":"\/documentation\/fido2\/publickeycredentialparameters"},"doc://com.ibm.iOS-SDK/documentation/FIDO2/PublicKeyCredentialUserEntity":{"role":"symbol","title":"PublicKeyCredentialUserEntity","fragments":[{"kind":"keyword","text":"struct"},{"kind":"text","text":" "},{"kind":"identifier","text":"PublicKeyCredentialUserEntity"}],"abstract":[{"type":"text","text":"Represents user account information provided when a credential is created."}],"identifier":"doc:\/\/com.ibm.iOS-SDK\/documentation\/FIDO2\/PublicKeyCredentialUserEntity","kind":"symbol","type":"topic","navigatorTitle":[{"kind":"identifier","text":"PublicKeyCredentialUserEntity"}],"url":"\/documentation\/fido2\/publickeycredentialuserentity"},"doc://com.ibm.iOS-SDK/documentation/FIDO2/AuthenticatorSelectionCriteria":{"role":"symbol","title":"AuthenticatorSelectionCriteria","fragments":[{"kind":"keyword","text":"struct"},{"kind":"text","text":" "},{"kind":"identifier","text":"AuthenticatorSelectionCriteria"}],"abstract":[{"type":"text","text":"WebAuthn Relying Parties may use the "},{"type":"codeVoice","code":"AuthenticatorSelectionCriteria"},{"type":"text","text":" dictionary to specify their requirements regarding authenticator attributes."}],"identifier":"doc:\/\/com.ibm.iOS-SDK\/documentation\/FIDO2\/AuthenticatorSelectionCriteria","kind":"symbol","type":"topic","navigatorTitle":[{"kind":"identifier","text":"AuthenticatorSelectionCriteria"}],"url":"\/documentation\/fido2\/authenticatorselectioncriteria"},"doc://com.ibm.iOS-SDK/documentation/FIDO2":{"role":"collection","title":"FIDO2","abstract":[],"identifier":"doc:\/\/com.ibm.iOS-SDK\/documentation\/FIDO2","kind":"symbol","type":"topic","url":"\/documentation\/fido2"}}}